CHANGES.txt
LICENSE.txt
README.txt
bootstrap.py
buildout.cfg
setup.py
src/p01/__init__.py
src/p01.zmi.egg-info/PKG-INFO
src/p01.zmi.egg-info/SOURCES.txt
src/p01.zmi.egg-info/dependency_links.txt
src/p01.zmi.egg-info/namespace_packages.txt
src/p01.zmi.egg-info/not-zip-safe
src/p01.zmi.egg-info/requires.txt
src/p01.zmi.egg-info/top_level.txt
src/p01/zmi/README.txt
src/p01/zmi/__init__.py
src/p01/zmi/breadcrumb.py
src/p01/zmi/breadcrumb.zcml
src/p01/zmi/configure.zcml
src/p01/zmi/error.py
src/p01/zmi/error.zcml
src/p01/zmi/ftesting.zcml
src/p01/zmi/interfaces.py
src/p01/zmi/layer.py
src/p01/zmi/layer.zcml
src/p01/zmi/sidebar.pt
src/p01/zmi/test_page.pt
src/p01/zmi/testing.py
src/p01/zmi/tests.py
src/p01/zmi/browser/__init__.py
src/p01/zmi/browser/configure.zcml
src/p01/zmi/browser/error.pt
src/p01/zmi/browser/error.py
src/p01/zmi/browser/error.zcml
src/p01/zmi/browser/error_as_text.pt
src/p01/zmi/browser/errors.pt
src/p01/zmi/browser/generatesample.pt
src/p01/zmi/browser/generation.py
src/p01/zmi/browser/generation_details.pt
src/p01/zmi/browser/generations.pt
src/p01/zmi/browser/generator.pt
src/p01/zmi/browser/process.zcml
src/p01/zmi/browser/registration.pt
src/p01/zmi/browser/runtimeinfo.pt
src/p01/zmi/browser/runtimeinfo.py
src/p01/zmi/browser/sampledata.pt
src/p01/zmi/browser/sampledata.py
src/p01/zmi/browser/sampledata.zcml
src/p01/zmi/browser/sampler.pt
src/p01/zmi/browser/sampler.py
src/p01/zmi/browser/sampler.zcml
src/p01/zmi/browser/samplergenerator.pt
src/p01/zmi/browser/samplergenerator_single.pt
src/p01/zmi/browser/sitemanager.pt
src/p01/zmi/browser/sitemanager.py
src/p01/zmi/browser/sitemanager.zcml
src/p01/zmi/browser/siteregistration.pt
src/p01/zmi/browser/zodbcontrol.pt
src/p01/zmi/browser/zodbcontrol.py
src/p01/zmi/menu/__init__.py
src/p01/zmi/menu/configure.zcml
src/p01/zmi/menu/menu.pt
src/p01/zmi/menu/site.py
src/p01/zmi/menu/site.zcml
src/p01/zmi/menu/sitemanager.py
src/p01/zmi/menu/sitemanager.zcml
src/p01/zmi/skin/README.txt
src/p01/zmi/skin/__init__.py
src/p01/zmi/skin/browser.zcml
src/p01/zmi/skin/configure.zcml
src/p01/zmi/skin/header.pt
src/p01/zmi/skin/header.py
src/p01/zmi/skin/header.zcml
src/p01/zmi/skin/jquery-1.3.2.min.js
src/p01/zmi/skin/p01.zmi-0.5.0.css
